mad_oauth2/__init__.py
mad_oauth2/admin.py
mad_oauth2/apps.py
mad_oauth2/models.py
mad_oauth2/oauth2.py
mad_oauth2/settings.py
mad_oauth2/signals.py
mad_oauth2/tasks.py
mad_oauth2/tests.py
mad_oauth2/throttling.py
mad_oauth2/utils.py
mad_oauth2/migrations/0001_initial.py
mad_oauth2/migrations/__init__.py
mad_oauth2-4.0.0.dist-info/licenses/LICENSE.md
mad_oauth2-4.0.0.dist-info/METADATA
mad_oauth2-4.0.0.dist-info/WHEEL
mad_oauth2-4.0.0.dist-info/top_level.txt
mad_oauth2-4.0.0.dist-info/RECORD
