Metadata-Version: 2.4
Name: mad_oauth2
Version: 4.0.0
Summary: A Django app extension of django-oauth-toolkit that implements scope based applications.
Home-page: https://www.madithouse.com/
Author: Haseeb Ur Rehman
Author-email: haseeb@madithouse.com
License: Other/Proprietary License
Classifier: Environment :: Web Environment
Classifier: Framework :: Django
Classifier: Intended Audience :: Developers
Classifier: License :: Other/Proprietary License
Classifier: Operating System :: OS Independent
Classifier: Programming Language :: Python
Classifier: Programming Language :: Python :: 3
Classifier: Programming Language :: Python :: 3.6
Classifier: Topic :: Internet :: WWW/HTTP
Classifier: Topic :: Internet :: WWW/HTTP :: Dynamic Content
Requires-Python: >=3.6
License-File: LICENSE.md
Requires-Dist: django>=4.2.6
Requires-Dist: djangorestframework>=3.14.0
Requires-Dist: celery>=5.3.4
Requires-Dist: django-celery-beat>=2.5.0
Requires-Dist: django-filter>=23.3
Requires-Dist: django-oauth-toolkit>=2.4.0
Requires-Dist: django-multiselectfield>=0.1.12
Dynamic: license-file
